[
  {
    "alias": "aardvark2019",
    "text": "Allen Aardvark",
    "value": "aaardvark",
    "key": "aaardvark"
  },
  {
    "alias": "bandicoot2019",
    "text": "Betty Bandicoot",
    "value": "bbandicoot",
    "key": "bbandicoot"
  },
  {
    "alias": "caribou2019",
    "text": "Cornelius Caribou",
    "value": "ccaribou",
    "key": "ccaribou"
  },
  {
    "alias": "duck2019",
    "text": "Daphne Duck",
    "value": "dduck",
    "key": "dduck"
  },
  {
    "alias": "elwood",
    "text": "Elwood Elephant",
    "value": "eelephant",
    "key": "eelephant"
  },
  {
    "alias": "fox2019",
    "text": "Fernanda Fox",
    "value": "ffox",
    "key": "ffox"
  },
  {
    "alias": "giraffe2019",
    "text": "Gonçalo Giraffe",
    "value": "ggiraffe",
    "key": "ggiraffe"
  }
]
